is_empty/Test.py
is_empty/__init__.py
is_empty/empty.py
is_empty-1.0.1.dist-info/LICENSE
is_empty-1.0.1.dist-info/METADATA
is_empty-1.0.1.dist-info/WHEEL
is_empty-1.0.1.dist-info/top_level.txt
is_empty-1.0.1.dist-info/RECORD
