Metadata-Version: 2.1
Name: is-empty
Version: 1.0.1
Summary: Python package to check whether a variable is empty or not.
Home-page: https://github.com/wskoly/is_empty/
Author: Wahid Sadique Koly
Author-email: wskoly.bp@gmail.com
License: MIT
Keywords: python,variable,is empty,empty,length
Classifier: Development Status :: 4 - Beta
Classifier: Intended Audience :: Developers
Classifier: Programming Language :: Python :: 3
Classifier: Operating System :: Unix
Classifier: Operating System :: MacOS :: MacOS X
Classifier: Operating System :: Microsoft :: Windows
License-File: LICENSE
